django_orm_performance_enhancers/__about__.py
django_orm_performance_enhancers/__init__.py
django_orm_performance_enhancers/descriptors.py
django_orm_performance_enhancers/evaluation_callbacks.py
django_orm_performance_enhancers/querysets.py
django_orm_performance_enhancers/select_related_hack.py
django_orm_performance_enhancers/utils.py
django_orm_performance_enhancers-1.0.1.dist-info/METADATA
django_orm_performance_enhancers-1.0.1.dist-info/WHEEL
django_orm_performance_enhancers-1.0.1.dist-info/licenses/LICENSE.txt
django_orm_performance_enhancers-1.0.1.dist-info/RECORD
