Metadata-Version: 2.4
Name: django-orm-performance-enhancers
Version: 1.0.1
Summary: A set of QuerySet performance enhancers for Django ORM
Project-URL: Documentation, https://github.com/imakedonsky/django-orm-performance-enhancers#readme
Project-URL: Issues, https://github.com/imakedonsky/django-orm-performance-enhancers/issues
Project-URL: Source, https://github.com/imakedonsky/django-orm-performance-enhancers
Author-email: Oleksandr Mashianov <mashianov@gmail.com>
License-Expression: MIT
License-File: LICENSE.txt
Classifier: Development Status :: 4 - Beta
Classifier: Programming Language :: Python
Classifier: Programming Language :: Python :: 3.7
Classifier: Programming Language :: Python :: 3.8
Classifier: Programming Language :: Python :: 3.9
Classifier: Programming Language :: Python :: 3.10
Classifier: Programming Language :: Python :: 3.11
Classifier: Programming Language :: Python :: Implementation :: CPython
Requires-Python: >=3.7
Requires-Dist: django-stubs
Requires-Dist: django>=3.2
Requires-Dist: psycopg2-binary>=2.8
Requires-Dist: typing-extensions
